fefiphopy/__init__.py
fefiphopy/_baseline_correction.py
fefiphopy/_get_data.py
fefiphopy/_methods.py
fefiphopy/_smooth.py
fefiphopy/_steps.py
fefiphopy-0.0.4.dist-info/LICENSE
fefiphopy-0.0.4.dist-info/METADATA
fefiphopy-0.0.4.dist-info/WHEEL
fefiphopy-0.0.4.dist-info/top_level.txt
fefiphopy-0.0.4.dist-info/RECORD
